douban/__init__.py
douban/album.py
douban_album_dl-0.0.1.data/scripts/douban-album-dl
douban_album_dl-0.0.1.dist-info/DESCRIPTION.rst
douban_album_dl-0.0.1.dist-info/METADATA
douban_album_dl-0.0.1.dist-info/RECORD
douban_album_dl-0.0.1.dist-info/WHEEL
douban_album_dl-0.0.1.dist-info/metadata.json
douban_album_dl-0.0.1.dist-info/top_level.txt
