Metadata-Version: 2.0
Name: douban-album-dl
Version: 0.0.1
Summary: douban album downloader
Home-page: https://github.com/delta4d/douban-album-dl
Author: delta
Author-email: UNKNOWN
License: MIT
Keywords: douban dl
Platform: UNKNOWN
Requires-Dist: bs4
Requires-Dist: requests
